dodoo_migrator/__init__.py
dodoo_migrator/cli.py
dodoo_migrator/migration_manager.py
dodoo_migrator/analyzer/__init__.py
dodoo_migrator/analyzer/env.py
dodoo_migrator/analyzer/git.py
dodoo_migrator/analyzer/data_analyzer/__init__.py
dodoo_migrator/analyzer/data_analyzer/_transitions.py
dodoo_migrator/analyzer/data_analyzer/analyzer.py
dodoo_migrator/analyzer/data_analyzer/reporter.py
dodoo_migrator/analyzer/schema_analyzer/__init__.py
dodoo_migrator/analyzer/schema_analyzer/_exceptions.py
dodoo_migrator/analyzer/schema_analyzer/_slots.py
dodoo_migrator/analyzer/schema_analyzer/_transitions.py
dodoo_migrator/analyzer/schema_analyzer/analyzer.py
dodoo_migrator/analyzer/schema_analyzer/reporter.py
dodoo_migrator/migration/__init__.py
dodoo_migrator/migration/database.py
dodoo_migrator/migration/exceptions.py
dodoo_migrator/migration/migration.py
dodoo_migrator/migration/upgradeservice/__init__.py
dodoo_migrator/migration/upgradeservice/db.py
dodoo_migrator/migration/upgradeservice/errors.py
dodoo_migrator/migration/upgradeservice/keys.py
dodoo_migrator/migration/upgradeservice/merge_copytree.py
dodoo_migrator/migration/upgradeservice/odoo_service.py
odoo/migration/__init__.py
odoo/migration/migration.py
dodoo_migrator-0.6.7.dist-info/LICENSE
dodoo_migrator-0.6.7.dist-info/METADATA
dodoo_migrator-0.6.7.dist-info/WHEEL
dodoo_migrator-0.6.7.dist-info/entry_points.txt
dodoo_migrator-0.6.7.dist-info/top_level.txt
dodoo_migrator-0.6.7.dist-info/RECORD
